climatic/CoreCli.py
climatic/Logger.py
climatic/__init__.py
climatic/cli/Linux.py
climatic/cli/__init__.py
climatic/connections/Connection.py
climatic/connections/Ser2Net.py
climatic/connections/Ssh.py
climatic/connections/Telnet.py
climatic/connections/__init__.py
climatic-0.0.4.dist-info/LICENSE
climatic-0.0.4.dist-info/METADATA
climatic-0.0.4.dist-info/WHEEL
climatic-0.0.4.dist-info/top_level.txt
climatic-0.0.4.dist-info/RECORD
