Metadata-Version: 2.1
Name: climatic
Version: 0.0.4
Summary: Tool to ease and automate CLI usage
Home-page: https://github.com/evedovelli/climatic
Author: Estevan Vedovelli
Author-email: evedovelli@gmail.com
License: UNKNOWN
Project-URL: Bug Tracker, https://github.com/evedovelli/climatic/issues
Platform: UNKNOWN
Classifier: Programming Language :: Python :: 3
Classifier: License :: OSI Approved :: MIT License
Classifier: Operating System :: OS Independent
Requires-Python: >=3.6
License-File: LICENSE
